uniseq/__init__.py
uniseq/main.py
uniseq-0.0.2.dist-info/LICENSE
uniseq-0.0.2.dist-info/METADATA
uniseq-0.0.2.dist-info/WHEEL
uniseq-0.0.2.dist-info/top_level.txt
uniseq-0.0.2.dist-info/RECORD
